
[
	{
		"nome": "Manoel Davi Leonardo Moura",
		"idade": 48,
		"cpf": "023.606.294-84",
		"rg": "37.298.169-0",
		"data_nasc": "20/08/1977",
		"sexo": "Masculino",
		"signo": "Leão",
		"mae": "Allana Liz",
		"pai": "Cauê Kauê Moura",
		"email": "manoel.davi.moura@acramisper.com",
		"senha": "uC1AaNR4HZ",
		"cep": "66910-200",
		"endereco": "Vila Aragão",
		"numero": 464,
		"bairro": "Vila (Mosqueiro)",
		"cidade": "Belém",
		"estado": "PA",
		"telefone_fixo": "(91) 3932-3289",
		"celular": "(91) 98943-1451",
		"altura": "1,79",
		"peso": 84,
		"tipo_sanguineo": "AB-",
		"cor": "azul"
	},
	{
		"nome": "Vitória Ester Assis",
		"idade": 24,
		"cpf": "396.657.734-88",
		"rg": "39.277.984-5",
		"data_nasc": "18/02/2001",
		"sexo": "Feminino",
		"signo": "Aquário",
		"mae": "Renata Nina",
		"pai": "Osvaldo Benedito Anderson Assis",
		"email": "vitoria_assis@leiloesjudiciais.com.br",
		"senha": "54YzGDyazp",
		"cep": "66822-590",
		"endereco": "Alameda dos Anjos",
		"numero": 686,
		"bairro": "Águas Negras (Icoaraci)",
		"cidade": "Belém",
		"estado": "PA",
		"telefone_fixo": "(91) 2838-8923",
		"celular": "(91) 99949-9495",
		"altura": "1,61",
		"peso": 83,
		"tipo_sanguineo": "A+",
		"cor": "azul"
	},
	{
		"nome": "Renata Liz Antonella Farias",
		"idade": 60,
		"cpf": "279.188.784-93",
		"rg": "23.825.565-7",
		"data_nasc": "13/08/1965",
		"sexo": "Feminino",
		"signo": "Leão",
		"mae": "Fernanda Jaqueline",
		"pai": "Yago Joaquim Farias",
		"email": "renata_farias@belbrindes.com",
		"senha": "X5a3oK6xxR",
		"cep": "66615-020",
		"endereco": "Passagem São Francisco",
		"numero": 130,
		"bairro": "Marambaia",
		"cidade": "Belém",
		"estado": "PA",
		"telefone_fixo": "(91) 2720-2390",
		"celular": "(91) 99640-1320",
		"altura": "1,52",
		"peso": 49,
		"tipo_sanguineo": "O+",
		"cor": "vermelho"
	},
	{
		"nome": "Sueli Tânia Jéssica Sales",
		"idade": 47,
		"cpf": "709.627.424-30",
		"rg": "17.011.020-5",
		"data_nasc": "11/02/1978",
		"sexo": "Feminino",
		"signo": "Aquário",
		"mae": "Nicole Carla",
		"pai": "Ryan Bernardo Bernardo Sales",
		"email": "sueli_sales@2registrocivil.com.br",
		"senha": "xaj9511XpO",
		"cep": "66843-532",
		"endereco": "Travessa Cristóvão Colombo",
		"numero": 858,
		"bairro": "Água Boa (Outeiro)",
		"cidade": "Belém",
		"estado": "PA",
		"telefone_fixo": "(91) 2968-1931",
		"celular": "(91) 99574-6019",
		"altura": "1,55",
		"peso": 82,
		"tipo_sanguineo": "B-",
		"cor": "preto"
	},
	{
		"nome": "Ryan Thomas Filipe Baptista",
		"idade": 39,
		"cpf": "116.302.524-09",
		"rg": "24.050.282-6",
		"data_nasc": "06/11/1986",
		"sexo": "Masculino",
		"signo": "Escorpião",
		"mae": "Patrícia Alessandra",
		"pai": "Benjamin Thomas Fábio Baptista",
		"email": "ryan-baptista80@yahho.com.br",
		"senha": "4znIZiFfAb",
		"cep": "66640-110",
		"endereco": "Passagem São Marcos",
		"numero": 955,
		"bairro": "Mangueirão",
		"cidade": "Belém",
		"estado": "PA",
		"telefone_fixo": "(91) 2727-0945",
		"celular": "(91) 99881-9514",
		"altura": "1,77",
		"peso": 53,
		"tipo_sanguineo": "AB-",
		"cor": "vermelho"
	},
	{
		"nome": "Mariana Isis Castro",
		"idade": 54,
		"cpf": "820.997.594-30",
		"rg": "42.469.616-2",
		"data_nasc": "17/08/1971",
		"sexo": "Feminino",
		"signo": "Leão",
		"mae": "Louise Liz",
		"pai": "José Thiago Anderson Castro",
		"email": "mariana_isis_castro@caej.com.br",
		"senha": "pU9cumhCNc",
		"cep": "66815-255",
		"endereco": "Alameda Freijó",
		"numero": 828,
		"bairro": "Maracacuera (Icoaraci)",
		"cidade": "Belém",
		"estado": "PA",
		"telefone_fixo": "(91) 3921-3944",
		"celular": "(91) 98942-4476",
		"altura": "1,71",
		"peso": 78,
		"tipo_sanguineo": "AB-",
		"cor": "amarelo"
	},
	{
		"nome": "Isis Isadora da Luz",
		"idade": 44,
		"cpf": "416.218.874-21",
		"rg": "34.478.620-1",
		"data_nasc": "13/04/1981",
		"sexo": "Feminino",
		"signo": "Áries",
		"mae": "Lara Juliana Márcia",
		"pai": "Augusto Lorenzo da Luz",
		"email": "isis_isadora_daluz@tribunadeindaia.com.br",
		"senha": "XJtfyq5hJb",
		"cep": "66625-424",
		"endereco": "Passagem Nazaré",
		"numero": 964,
		"bairro": "Cabanagem",
		"cidade": "Belém",
		"estado": "PA",
		"telefone_fixo": "(91) 2800-6727",
		"celular": "(91) 99567-1165",
		"altura": "1,58",
		"peso": 78,
		"tipo_sanguineo": "O+",
		"cor": "vermelho"
	},
	{
		"nome": "Gabriel Osvaldo Thomas Carvalho",
		"idade": 57,
		"cpf": "903.764.924-65",
		"rg": "33.889.642-9",
		"data_nasc": "16/09/1968",
		"sexo": "Masculino",
		"signo": "Virgem",
		"mae": "Sebastiana Lara Jennifer",
		"pai": "Anderson Lucas Carvalho",
		"email": "gabriel-carvalho93@gmailo.com",
		"senha": "yQY5IlDa3q",
		"cep": "66055-240",
		"endereco": "Avenida Generalíssimo Deodoro",
		"numero": 232,
		"bairro": "Umarizal",
		"cidade": "Belém",
		"estado": "PA",
		"telefone_fixo": "(91) 3961-1945",
		"celular": "(91) 99255-7368",
		"altura": "1,80",
		"peso": 73,
		"tipo_sanguineo": "B-",
		"cor": "roxo"
	},
	{
		"nome": "Marcos Lucas Isaac Melo",
		"idade": 59,
		"cpf": "830.506.574-05",
		"rg": "21.606.923-3",
		"data_nasc": "01/02/1966",
		"sexo": "Masculino",
		"signo": "Aquário",
		"mae": "Maitê Nair",
		"pai": "Theo Victor André Melo",
		"email": "marcos_melo@edpbr.com.br",
		"senha": "Kg1a2Me7JT",
		"cep": "66055-060",
		"endereco": "Vila Aragão",
		"numero": 559,
		"bairro": "Umarizal",
		"cidade": "Belém",
		"estado": "PA",
		"telefone_fixo": "(91) 3633-0807",
		"celular": "(91) 98562-1419",
		"altura": "1,79",
		"peso": 83,
		"tipo_sanguineo": "B+",
		"cor": "roxo"
	},
	{
		"nome": "Luna Evelyn da Cunha",
		"idade": 77,
		"cpf": "876.127.124-15",
		"rg": "50.460.700-5",
		"data_nasc": "12/07/1948",
		"sexo": "Feminino",
		"signo": "Câncer",
		"mae": "Flávia Eloá",
		"pai": "Edson Augusto da Cunha",
		"email": "luna.evelyn.dacunha@ticem.com.br",
		"senha": "L9EGB4Dfaz",
		"cep": "66083-000",
		"endereco": "Travessa Mauriti",
		"numero": 127,
		"bairro": "Telégrafo Sem Fio",
		"cidade": "Belém",
		"estado": "PA",
		"telefone_fixo": "(91) 2834-0721",
		"celular": "(91) 98370-3282",
		"altura": "1,58",
		"peso": 55,
		"tipo_sanguineo": "B-",
		"cor": "verde"
	},
	{
		"nome": "Carlos Renato Thomas Nunes",
		"idade": 70,
		"cpf": "640.124.304-08",
		"rg": "33.083.654-7",
		"data_nasc": "19/06/1955",
		"sexo": "Masculino",
		"signo": "Gêmeos",
		"mae": "Jéssica Benedita Lavínia",
		"pai": "Henry Jorge Leandro Nunes",
		"email": "carlos_renato_nunes@etipel.com.br",
		"senha": "lEM8znO4co",
		"cep": "66820-315",
		"endereco": "Rua Magalhães Barata",
		"numero": 830,
		"bairro": "Tenoné",
		"cidade": "Belém",
		"estado": "PA",
		"telefone_fixo": "(91) 2882-4208",
		"celular": "(91) 99755-9002",
		"altura": "1,76",
		"peso": 90,
		"tipo_sanguineo": "O-",
		"cor": "amarelo"
	},
	{
		"nome": "Raul Iago Cavalcanti",
		"idade": 35,
		"cpf": "407.227.284-17",
		"rg": "25.005.004-3",
		"data_nasc": "17/01/1990",
		"sexo": "Masculino",
		"signo": "Capricórnio",
		"mae": "Emily Renata",
		"pai": "Enzo Tiago Rodrigo Cavalcanti",
		"email": "raul-cavalcanti93@isometro.com.br",
		"senha": "BcDIYD2s2B",
		"cep": "66919-310",
		"endereco": "Rua Orquídeas",
		"numero": 276,
		"bairro": "Ariramba (Mosqueiro)",
		"cidade": "Belém",
		"estado": "PA",
		"telefone_fixo": "(91) 3726-0327",
		"celular": "(91) 98688-9186",
		"altura": "1,96",
		"peso": 68,
		"tipo_sanguineo": "AB+",
		"cor": "preto"
	},
	{
		"nome": "Sara Larissa Ester Rodrigues",
		"idade": 41,
		"cpf": "312.761.974-03",
		"rg": "12.541.937-5",
		"data_nasc": "16/09/1984",
		"sexo": "Feminino",
		"signo": "Virgem",
		"mae": "Eduarda Alana",
		"pai": "Matheus Noah Rodrigues",
		"email": "sara.larissa.rodrigues@cernizza.com.br",
		"senha": "5FclbMAI86",
		"cep": "66123-460",
		"endereco": "Passagem Doutor Luís Régis",
		"numero": 962,
		"bairro": "Sacramenta",
		"cidade": "Belém",
		"estado": "PA",
		"telefone_fixo": "(91) 2598-3933",
		"celular": "(91) 99934-5739",
		"altura": "1,79",
		"peso": 58,
		"tipo_sanguineo": "AB+",
		"cor": "preto"
	},
	{
		"nome": "Caroline Stella Sueli Martins",
		"idade": 24,
		"cpf": "226.187.934-20",
		"rg": "20.220.048-6",
		"data_nasc": "24/09/2001",
		"sexo": "Feminino",
		"signo": "Libra",
		"mae": "Bianca Heloisa",
		"pai": "Yago Vicente Eduardo Martins",
		"email": "carolinestellamartins@rgsa.com.br",
		"senha": "kI1r8anyoS",
		"cep": "66815-410",
		"endereco": "Passagem Santa Maria",
		"numero": 478,
		"bairro": "Maracacuera (Icoaraci)",
		"cidade": "Belém",
		"estado": "PA",
		"telefone_fixo": "(91) 2538-7321",
		"celular": "(91) 98782-3731",
		"altura": "1,62",
		"peso": 54,
		"tipo_sanguineo": "A-",
		"cor": "amarelo"
	},
	{
		"nome": "Raimunda Camila Almada",
		"idade": 75,
		"cpf": "154.674.624-23",
		"rg": "40.144.591-4",
		"data_nasc": "19/04/1950",
		"sexo": "Feminino",
		"signo": "Áries",
		"mae": "Emily Gabrielly Luciana",
		"pai": "Pedro Henrique Caio Almada",
		"email": "raimunda-almada78@pciinformatica.com",
		"senha": "LGSy7WhJkc",
		"cep": "66077-710",
		"endereco": "Passagem São Raimundo",
		"numero": 242,
		"bairro": "Terra Firme",
		"cidade": "Belém",
		"estado": "PA",
		"telefone_fixo": "(91) 2795-4772",
		"celular": "(91) 99837-4640",
		"altura": "1,53",
		"peso": 49,
		"tipo_sanguineo": "O-",
		"cor": "roxo"
	},
	{
		"nome": "Brenda Clarice Oliveira",
		"idade": 78,
		"cpf": "447.122.514-68",
		"rg": "46.866.674-6",
		"data_nasc": "06/06/1947",
		"sexo": "Feminino",
		"signo": "Gêmeos",
		"mae": "Isabelly Joana",
		"pai": "Nicolas Caleb Manoel Oliveira",
		"email": "brenda_oliveira@yahoo.se",
		"senha": "EOAuBPgE2J",
		"cep": "66816-740",
		"endereco": "Passagem Fé em Deus",
		"numero": 269,
		"bairro": "Pratinha (Icoaraci)",
		"cidade": "Belém",
		"estado": "PA",
		"telefone_fixo": "(91) 2771-0332",
		"celular": "(91) 99525-9091",
		"altura": "1,68",
		"peso": 54,
		"tipo_sanguineo": "B-",
		"cor": "vermelho"
	},
	{
		"nome": "Sérgio Lucas Lopes",
		"idade": 34,
		"cpf": "133.692.364-43",
		"rg": "22.468.571-5",
		"data_nasc": "03/10/1991",
		"sexo": "Masculino",
		"signo": "Libra",
		"mae": "Marcela Emilly Raimunda",
		"pai": "Juan Manoel Alexandre Lopes",
		"email": "sergio.lucas.lopes@thewishes.com.br",
		"senha": "GJbxbOo1TT",
		"cep": "66823-092",
		"endereco": "Quadra Vinte e Cinco",
		"numero": 366,
		"bairro": "Coqueiro",
		"cidade": "Belém",
		"estado": "PA",
		"telefone_fixo": "(91) 3574-4628",
		"celular": "(91) 99815-6095",
		"altura": "1,99",
		"peso": 88,
		"tipo_sanguineo": "A-",
		"cor": "azul"
	},
	{
		"nome": "André Cláudio Ribeiro",
		"idade": 48,
		"cpf": "248.644.544-77",
		"rg": "20.052.383-1",
		"data_nasc": "01/11/1977",
		"sexo": "Masculino",
		"signo": "Escorpião",
		"mae": "Yasmin Helena",
		"pai": "Manuel Filipe Ribeiro",
		"email": "andreclaudioribeiro@mtc.eng.br",
		"senha": "cRNzz4Nlj3",
		"cep": "66115-216",
		"endereco": "Alameda de Libra",
		"numero": 394,
		"bairro": "Val-de-Cães",
		"cidade": "Belém",
		"estado": "PA",
		"telefone_fixo": "(91) 2526-6531",
		"celular": "(91) 99163-8096",
		"altura": "1,74",
		"peso": 90,
		"tipo_sanguineo": "A+",
		"cor": "preto"
	},
	{
		"nome": "Tereza Rosângela Kamilly Costa",
		"idade": 58,
		"cpf": "428.264.154-17",
		"rg": "21.874.436-5",
		"data_nasc": "27/01/1967",
		"sexo": "Feminino",
		"signo": "Aquário",
		"mae": "Rita Carolina",
		"pai": "Diego Daniel Daniel Costa",
		"email": "tereza_rosangela_costa@oxiteno.com",
		"senha": "MkYdsKtqxi",
		"cep": "66010-070",
		"endereco": "Avenida Marechal Hermes",
		"numero": 768,
		"bairro": "Campina",
		"cidade": "Belém",
		"estado": "PA",
		"telefone_fixo": "(91) 3730-7670",
		"celular": "(91) 98197-0616",
		"altura": "1,55",
		"peso": 78,
		"tipo_sanguineo": "O-",
		"cor": "vermelho"
	},
	{
		"nome": "Marina Clara Pinto",
		"idade": 40,
		"cpf": "407.236.344-83",
		"rg": "32.937.677-9",
		"data_nasc": "04/05/1985",
		"sexo": "Feminino",
		"signo": "Touro",
		"mae": "Lara Stella Sara",
		"pai": "Gustavo André Luiz Pinto",
		"email": "marina.clara.pinto@ornatopresentes.com.br",
		"senha": "jNOw0td2eP",
		"cep": "66026-306",
		"endereco": "Vila Natércia",
		"numero": 373,
		"bairro": "Jurunas",
		"cidade": "Belém",
		"estado": "PA",
		"telefone_fixo": "(91) 2635-3058",
		"celular": "(91) 99145-3538",
		"altura": "1,50",
		"peso": 65,
		"tipo_sanguineo": "O+",
		"cor": "verde"
	},
	{
		"nome": "Marcela Daiane Drumond",
		"idade": 45,
		"cpf": "355.227.554-15",
		"rg": "39.127.535-5",
		"data_nasc": "07/03/1980",
		"sexo": "Feminino",
		"signo": "Peixes",
		"mae": "Isabella Eduarda Aline",
		"pai": "Ricardo Caleb Enrico Drumond",
		"email": "marcela-drumond70@portalpublicidade.com.br",
		"senha": "H9nJSOBoxa",
		"cep": "66087-380",
		"endereco": "Passagem Grão Pará",
		"numero": 439,
		"bairro": "Marco",
		"cidade": "Belém",
		"estado": "PA",
		"telefone_fixo": "(91) 3653-4020",
		"celular": "(91) 99918-1126",
		"altura": "1,82",
		"peso": 53,
		"tipo_sanguineo": "B+",
		"cor": "verde"
	},
	{
		"nome": "Letícia Sebastiana Emily Barros",
		"idade": 79,
		"cpf": "337.003.534-05",
		"rg": "25.152.171-0",
		"data_nasc": "09/06/1946",
		"sexo": "Feminino",
		"signo": "Gêmeos",
		"mae": "Sebastiana Camila",
		"pai": "Francisco Felipe Barros",
		"email": "leticiasebastianabarros@sfreitasadvogados.com.br",
		"senha": "a8qTozzzEx",
		"cep": "66633-090",
		"endereco": "Alameda dos Sorrisos",
		"numero": 191,
		"bairro": "Parque Verde",
		"cidade": "Belém",
		"estado": "PA",
		"telefone_fixo": "(91) 2954-0140",
		"celular": "(91) 99284-4340",
		"altura": "1,81",
		"peso": 69,
		"tipo_sanguineo": "AB-",
		"cor": "verde"
	},
	{
		"nome": "Regina Hadassa Beatriz Figueiredo",
		"idade": 34,
		"cpf": "938.890.414-18",
		"rg": "49.041.888-0",
		"data_nasc": "15/03/1991",
		"sexo": "Feminino",
		"signo": "Peixes",
		"mae": "Brenda Fernanda",
		"pai": "Vitor Anthony Joaquim Figueiredo",
		"email": "reginahadassafigueiredo@focusgrafica.com.br",
		"senha": "qX8BdnlJuE",
		"cep": "66810-490",
		"endereco": "Vila Matos Costa",
		"numero": 663,
		"bairro": "Cruzeiro (Icoaraci)",
		"cidade": "Belém",
		"estado": "PA",
		"telefone_fixo": "(91) 2892-8470",
		"celular": "(91) 98533-7945",
		"altura": "1,61",
		"peso": 68,
		"tipo_sanguineo": "A+",
		"cor": "vermelho"
	},
	{
		"nome": "Anthony Manuel Elias Silva",
		"idade": 65,
		"cpf": "526.849.424-47",
		"rg": "11.858.572-1",
		"data_nasc": "07/10/1960",
		"sexo": "Masculino",
		"signo": "Libra",
		"mae": "Mirella Jennifer",
		"pai": "Nathan Tomás Cláudio Silva",
		"email": "anthony_silva@alstom.com",
		"senha": "FdEZ7N9CaF",
		"cep": "66079-230",
		"endereco": "Rua da Vitória",
		"numero": 583,
		"bairro": "Guamá",
		"cidade": "Belém",
		"estado": "PA",
		"telefone_fixo": "(91) 2678-4285",
		"celular": "(91) 99305-1278",
		"altura": "1,65",
		"peso": 92,
		"tipo_sanguineo": "B+",
		"cor": "verde"
	},
	{
		"nome": "Heitor Vitor Daniel Alves",
		"idade": 76,
		"cpf": "720.873.494-10",
		"rg": "28.636.538-8",
		"data_nasc": "06/04/1949",
		"sexo": "Masculino",
		"signo": "Áries",
		"mae": "Lívia Heloisa",
		"pai": "Calebe Nathan Alves",
		"email": "heitor_vitor_alves@valeguinchos.com.br",
		"senha": "w5n1B5oi2X",
		"cep": "66090-640",
		"endereco": "Bloco Trinta e Cinco",
		"numero": 622,
		"bairro": "São Brás",
		"cidade": "Belém",
		"estado": "PA",
		"telefone_fixo": "(91) 2710-8319",
		"celular": "(91) 99222-9166",
		"altura": "1,81",
		"peso": 86,
		"tipo_sanguineo": "O+",
		"cor": "azul"
	},
	{
		"nome": "Brenda Carolina Letícia Peixoto",
		"idade": 37,
		"cpf": "008.964.054-35",
		"rg": "34.509.519-4",
		"data_nasc": "11/03/1988",
		"sexo": "Feminino",
		"signo": "Peixes",
		"mae": "Elaine Mariana Sophie",
		"pai": "José Caio Peixoto",
		"email": "brenda-peixoto80@sdrifs.com.br",
		"senha": "i2lXUrWffR",
		"cep": "66635-495",
		"endereco": "Alameda Quinze de Maio",
		"numero": 435,
		"bairro": "Parque Verde",
		"cidade": "Belém",
		"estado": "PA",
		"telefone_fixo": "(91) 2673-6043",
		"celular": "(91) 98642-0367",
		"altura": "1,59",
		"peso": 61,
		"tipo_sanguineo": "O+",
		"cor": "preto"
	},
	{
		"nome": "Mariana Lara Kamilly Pereira",
		"idade": 31,
		"cpf": "799.711.134-49",
		"rg": "29.255.232-4",
		"data_nasc": "18/05/1994",
		"sexo": "Feminino",
		"signo": "Touro",
		"mae": "Regina Daiane Analu",
		"pai": "Diego Lucas Pereira",
		"email": "marianalarapereira@br.rhodia.com",
		"senha": "rrUPxWnONi",
		"cep": "66075-240",
		"endereco": "Passagem São Lázaro",
		"numero": 237,
		"bairro": "Guamá",
		"cidade": "Belém",
		"estado": "PA",
		"telefone_fixo": "(91) 3726-4887",
		"celular": "(91) 98909-4166",
		"altura": "1,56",
		"peso": 85,
		"tipo_sanguineo": "AB+",
		"cor": "roxo"
	},
	{
		"nome": "Jaqueline Caroline da Mota",
		"idade": 74,
		"cpf": "086.379.944-23",
		"rg": "36.319.171-9",
		"data_nasc": "05/01/1951",
		"sexo": "Feminino",
		"signo": "Capricórnio",
		"mae": "Lavínia Fabiana",
		"pai": "Thales Henrique Gustavo da Mota",
		"email": "jaqueline.caroline.damota@costaporto.com.br",
		"senha": "UUAgBQZBeW",
		"cep": "66032-080",
		"endereco": "Vila Padre Antônio Vieira",
		"numero": 573,
		"bairro": "Condor",
		"cidade": "Belém",
		"estado": "PA",
		"telefone_fixo": "(91) 2770-1295",
		"celular": "(91) 99987-7217",
		"altura": "1,62",
		"peso": 80,
		"tipo_sanguineo": "O-",
		"cor": "verde"
	},
	{
		"nome": "Renan Nelson da Costa",
		"idade": 35,
		"cpf": "274.584.154-87",
		"rg": "10.706.346-3",
		"data_nasc": "12/06/1990",
		"sexo": "Masculino",
		"signo": "Gêmeos",
		"mae": "Luana Evelyn",
		"pai": "Renato Luan da Costa",
		"email": "renannelsondacosta@tam.com.br",
		"senha": "XtrrZ7hb7Z",
		"cep": "66822-070",
		"endereco": "Rua E",
		"numero": 883,
		"bairro": "Águas Negras (Icoaraci)",
		"cidade": "Belém",
		"estado": "PA",
		"telefone_fixo": "(91) 3813-2644",
		"celular": "(91) 99506-8070",
		"altura": "1,72",
		"peso": 103,
		"tipo_sanguineo": "AB-",
		"cor": "preto"
	},
	{
		"nome": "Tereza Caroline Barbosa",
		"idade": 78,
		"cpf": "049.668.104-42",
		"rg": "32.800.969-6",
		"data_nasc": "06/08/1947",
		"sexo": "Feminino",
		"signo": "Leão",
		"mae": "Maitê Aline Sophia",
		"pai": "Osvaldo Iago Pedro Barbosa",
		"email": "tereza.caroline.barbosa@bodyfast.com.br",
		"senha": "0yJeQJijf0",
		"cep": "66640-124",
		"endereco": "Rua Santo Antonio",
		"numero": 827,
		"bairro": "Mangueirão",
		"cidade": "Belém",
		"estado": "PA",
		"telefone_fixo": "(91) 3821-1243",
		"celular": "(91) 99456-0669",
		"altura": "1,79",
		"peso": 48,
		"tipo_sanguineo": "A+",
		"cor": "verde"
	}
]
